{
  "0": {
    "basicblocks": 1,
    "calls": "2 3 4",
    "file": "dct.c",
    "fileloc": 115,
    "instructions": 10,
    "name": "dct",
    "total_instructions": 270
  },
  "1": {
    "basicblocks": 5,
    "calls": "",
    "file": "dct.c",
    "fileloc": 30,
    "instructions": 77,
    "loads": {
      "G": 8,
      "L": 8
    },
    "name": "dct_1d",
    "stores": {
      "L": 1
    },
    "total_instructions": 77
  },
  "2": {
    "basicblocks": 6,
    "calls": "",
    "file": "dct.c",
    "fileloc": 87,
    "instructions": 21,
    "loads": {
      "L": 1
    },
    "name": "read_data",
    "stores": {
      "L": 1
    },
    "total_instructions": 21
  },
  "3": {
    "basicblocks": 17,
    "calls": "1 1",
    "file": "dct.c",
    "fileloc": 50,
    "instructions": 64,
    "loads": {
      "L": 2
    },
    "name": "dct_2d",
    "stores": {
      "L": 2
    },
    "total_instructions": 218
  },
  "4": {
    "basicblocks": 6,
    "calls": "",
    "file": "dct.c",
    "fileloc": 101,
    "instructions": 21,
    "loads": {
      "L": 1
    },
    "name": "write_data",
    "stores": {
      "L": 1
    },
    "total_instructions": 21
  }
}