{
  "0": {
    "basicblocks": 1,
    "calls": "2 4 3",
    "file": "dct.c",
    "fileloc": 116,
    "instructions": 11,
    "name": "dct",
    "total_instructions": 272
  },
  "1": {
    "basicblocks": 5,
    "calls": "",
    "file": "dct.c",
    "fileloc": 30,
    "instructions": 77,
    "loads": {
      "G": 8,
      "L": 8
    },
    "name": "dct_1d",
    "stores": {
      "L": 1
    },
    "total_instructions": 77
  },
  "2": {
    "basicblocks": 6,
    "calls": "",
    "file": "dct.c",
    "fileloc": 88,
    "instructions": 21,
    "loads": {
      "L": 1
    },
    "name": "read_data",
    "stores": {
      "L": 1
    },
    "total_instructions": 21
  },
  "3": {
    "basicblocks": 6,
    "calls": "",
    "file": "dct.c",
    "fileloc": 102,
    "instructions": 21,
    "loads": {
      "L": 1
    },
    "name": "write_data",
    "stores": {
      "L": 1
    },
    "total_instructions": 21
  },
  "4": {
    "basicblocks": 17,
    "calls": "1 1",
    "file": "dct.c",
    "fileloc": 50,
    "instructions": 65,
    "loads": {
      "L": 2
    },
    "name": "dct_2d",
    "stores": {
      "L": 2
    },
    "total_instructions": 219
  }
}