<profile>

<RTLDesignHierarchy>
<TopModule>
<ModuleName>dct</ModuleName>
<InstancesList>
<Instance>
<InstName>read_data_U0</InstName>
<ModuleName>read_data</ModuleName>
<IsCompInst>true</IsCompInst>
<ID>144</ID>
</Instance>
<Instance>
<InstName>Loop_Row_DCT_Loop_proc_U0</InstName>
<ModuleName>Loop_Row_DCT_Loop_proc</ModuleName>
<IsCompInst>true</IsCompInst>
<ID>166</ID>
</Instance>
<Instance>
<InstName>Loop_Xpose_Row_Outer_Loop_proc_U0</InstName>
<ModuleName>Loop_Xpose_Row_Outer_Loop_proc</ModuleName>
<IsCompInst>true</IsCompInst>
<ID>195</ID>
</Instance>
<Instance>
<InstName>Loop_Col_DCT_Loop_proc_U0</InstName>
<ModuleName>Loop_Col_DCT_Loop_proc</ModuleName>
<IsCompInst>true</IsCompInst>
<ID>208</ID>
</Instance>
<Instance>
<InstName>Loop_Xpose_Col_Outer_Loop_proc_U0</InstName>
<ModuleName>Loop_Xpose_Col_Outer_Loop_proc</ModuleName>
<IsCompInst>true</IsCompInst>
<ID>237</ID>
</Instance>
<Instance>
<InstName>write_data_U0</InstName>
<ModuleName>write_data</ModuleName>
<IsCompInst>true</IsCompInst>
<ID>243</ID>
</Instance>
</InstancesList>
</TopModule>
</RTLDesignHierarchy>

<ModuleInformation>
<Module>
<Name>read_data</Name>
<Loops>
<RD_Loop_Row_RD_Loop_Col></RD_Loop_Row_RD_Loop_Col>
</Loops>
<PerformanceEstimates>
<SummaryOfTimingAnalysis>
<TargetClockPeriod>10.00</TargetClockPeriod>
<ClockUncertainty>2.70</ClockUncertainty>
<EstimatedClockPeriod>6.082</EstimatedClockPeriod>
</SummaryOfTimingAnalysis>
<SummaryOfOverallLatency>
<Best-caseLatency>67</Best-caseLatency>
<Average-caseLatency>67</Average-caseLatency>
<Worst-caseLatency>67</Worst-caseLatency>
<Best-caseRealTimeLatency>0.670 us</Best-caseRealTimeLatency>
<Average-caseRealTimeLatency>0.670 us</Average-caseRealTimeLatency>
<Worst-caseRealTimeLatency>0.670 us</Worst-caseRealTimeLatency>
<PipelineInitiationInterval>65</PipelineInitiationInterval>
<PipelineType>loop auto-rewind stp (delay=1 clock cycles(s))</PipelineType>
</SummaryOfOverallLatency>
<SummaryOfLoopLatency>
<RD_Loop_Row_RD_Loop_Col>
<Name>RD_Loop_Row_RD_Loop_Col</Name>
<Slack>7.30</Slack>
<TripCount>64</TripCount>
<Latency>65</Latency>
<AbsoluteTimeLatency>0.650 us</AbsoluteTimeLatency>
<PipelineII>1</PipelineII>
<PipelineDepth>3</PipelineDepth>
<PipelineType>yes</PipelineType>
<InstanceList>
</InstanceList>
</RD_Loop_Row_RD_Loop_Col>
</SummaryOfLoopLatency>
<SummaryOfViolations>
<IssueType>-</IssueType>
<ViolationType>-</ViolationType>
<SourceLocation>E:/robot/project/xilinx_fpga_class/hls/lab3/dct.c:96</SourceLocation>
<SummaryOfLoopViolations>
<RD_Loop_Row_RD_Loop_Col>
<Name>RD_Loop_Row_RD_Loop_Col</Name>
<IssueType>-</IssueType>
<ViolationType>-</ViolationType>
<SourceLocation>E:/robot/project/xilinx_fpga_class/hls/lab3/dct.c:96</SourceLocation>
</RD_Loop_Row_RD_Loop_Col>
</SummaryOfLoopViolations>
</SummaryOfViolations>
</PerformanceEstimates>
<AreaEstimates>
<Resources>
<FF>44</FF>
<AVAIL_FF>106400</AVAIL_FF>
<UTIL_FF>~0</UTIL_FF>
<LUT>178</LUT>
<AVAIL_LUT>53200</AVAIL_LUT>
<UTIL_LUT>~0</UTIL_LUT>
<BRAM_18K>0</BRAM_18K>
<AVAIL_BRAM>280</AVAIL_BRAM>
<UTIL_BRAM>0</UTIL_BRAM>
<DSP>0</DSP>
<AVAIL_DSP>220</AVAIL_DSP>
<UTIL_DSP>0</UTIL_DSP>
<URAM>0</URAM>
<AVAIL_URAM>0</AVAIL_URAM>
<UTIL_URAM>0</UTIL_URAM>
</Resources>
</AreaEstimates>
<InterfaceSummary>
<RtlPorts>
<name>ap_clk</name>
<Object>read_data</Object>
<Type>return value</Type>
<Scope></Scope>
<IOProtocol>ap_ctrl_hs</IOProtocol>
<IOConfig></IOConfig>
<Dir>in</Dir>
<Bits>1</Bits>
<Attribute>control</Attribute>
</RtlPorts>
<RtlPorts>
<name>ap_rst</name>
<Object>read_data</Object>
<Type>return value</Type>
<Scope></Scope>
<IOProtocol>ap_ctrl_hs</IOProtocol>
<IOConfig></IOConfig>
<Dir>in</Dir>
<Bits>1</Bits>
<Attribute>control</Attribute>
</RtlPorts>
<RtlPorts>
<name>ap_start</name>
<Object>read_data</Object>
<Type>return value</Type>
<Scope></Scope>
<IOProtocol>ap_ctrl_hs</IOProtocol>
<IOConfig></IOConfig>
<Dir>in</Dir>
<Bits>1</Bits>
<Attribute>control</Attribute>
</RtlPorts>
<RtlPorts>
<name>ap_done</name>
<Object>read_data</Object>
<Type>return value</Type>
<Scope></Scope>
<IOProtocol>ap_ctrl_hs</IOProtocol>
<IOConfig></IOConfig>
<Dir>out</Dir>
<Bits>1</Bits>
<Attribute>control</Attribute>
</RtlPorts>
<RtlPorts>
<name>ap_continue</name>
<Object>read_data</Object>
<Type>return value</Type>
<Scope></Scope>
<IOProtocol>ap_ctrl_hs</IOProtocol>
<IOConfig></IOConfig>
<Dir>in</Dir>
<Bits>1</Bits>
<Attribute>control</Attribute>
</RtlPorts>
<RtlPorts>
<name>ap_idle</name>
<Object>read_data</Object>
<Type>return value</Type>
<Scope></Scope>
<IOProtocol>ap_ctrl_hs</IOProtocol>
<IOConfig></IOConfig>
<Dir>out</Dir>
<Bits>1</Bits>
<Attribute>control</Attribute>
</RtlPorts>
<RtlPorts>
<name>ap_ready</name>
<Object>read_data</Object>
<Type>return value</Type>
<Scope></Scope>
<IOProtocol>ap_ctrl_hs</IOProtocol>
<IOConfig></IOConfig>
<Dir>out</Dir>
<Bits>1</Bits>
<Attribute>control</Attribute>
</RtlPorts>
<RtlPorts>
<name>input_r_address0</name>
<Object>input_r</Object>
<Type>array</Type>
<Scope></Scope>
<IOProtocol>ap_memory</IOProtocol>
<IOConfig></IOConfig>
<Dir>out</Dir>
<Bits>6</Bits>
<Attribute>address</Attribute>
</RtlPorts>
<RtlPorts>
<name>input_r_ce0</name>
<Object>input_r</Object>
<Type>array</Type>
<Scope></Scope>
<IOProtocol>ap_memory</IOProtocol>
<IOConfig></IOConfig>
<Dir>out</Dir>
<Bits>1</Bits>
<Attribute>control</Attribute>
</RtlPorts>
<RtlPorts>
<name>input_r_q0</name>
<Object>input_r</Object>
<Type>array</Type>
<Scope></Scope>
<IOProtocol>ap_memory</IOProtocol>
<IOConfig></IOConfig>
<Dir>in</Dir>
<Bits>16</Bits>
<Attribute>data</Attribute>
</RtlPorts>
<RtlPorts>
<name>buf_0_address0</name>
<Object>buf_0</Object>
<Type>array</Type>
<Scope></Scope>
<IOProtocol>ap_memory</IOProtocol>
<IOConfig></IOConfig>
<Dir>out</Dir>
<Bits>3</Bits>
<Attribute>address</Attribute>
</RtlPorts>
<RtlPorts>
<name>buf_0_ce0</name>
<Object>buf_0</Object>
<Type>array</Type>
<Scope></Scope>
<IOProtocol>ap_memory</IOProtocol>
<IOConfig></IOConfig>
<Dir>out</Dir>
<Bits>1</Bits>
<Attribute>control</Attribute>
</RtlPorts>
<RtlPorts>
<name>buf_0_we0</name>
<Object>buf_0</Object>
<Type>array</Type>
<Scope></Scope>
<IOProtocol>ap_memory</IOProtocol>
<IOConfig></IOConfig>
<Dir>out</Dir>
<Bits>1</Bits>
<Attribute>control</Attribute>
</RtlPorts>
<RtlPorts>
<name>buf_0_d0</name>
<Object>buf_0</Object>
<Type>array</Type>
<Scope></Scope>
<IOProtocol>ap_memory</IOProtocol>
<IOConfig></IOConfig>
<Dir>out</Dir>
<Bits>16</Bits>
<Attribute>data</Attribute>
</RtlPorts>
<RtlPorts>
<name>buf_1_address0</name>
<Object>buf_1</Object>
<Type>array</Type>
<Scope></Scope>
<IOProtocol>ap_memory</IOProtocol>
<IOConfig></IOConfig>
<Dir>out</Dir>
<Bits>3</Bits>
<Attribute>address</Attribute>
</RtlPorts>
<RtlPorts>
<name>buf_1_ce0</name>
<Object>buf_1</Object>
<Type>array</Type>
<Scope></Scope>
<IOProtocol>ap_memory</IOProtocol>
<IOConfig></IOConfig>
<Dir>out</Dir>
<Bits>1</Bits>
<Attribute>control</Attribute>
</RtlPorts>
<RtlPorts>
<name>buf_1_we0</name>
<Object>buf_1</Object>
<Type>array</Type>
<Scope></Scope>
<IOProtocol>ap_memory</IOProtocol>
<IOConfig></IOConfig>
<Dir>out</Dir>
<Bits>1</Bits>
<Attribute>control</Attribute>
</RtlPorts>
<RtlPorts>
<name>buf_1_d0</name>
<Object>buf_1</Object>
<Type>array</Type>
<Scope></Scope>
<IOProtocol>ap_memory</IOProtocol>
<IOConfig></IOConfig>
<Dir>out</Dir>
<Bits>16</Bits>
<Attribute>data</Attribute>
</RtlPorts>
<RtlPorts>
<name>buf_2_address0</name>
<Object>buf_2</Object>
<Type>array</Type>
<Scope></Scope>
<IOProtocol>ap_memory</IOProtocol>
<IOConfig></IOConfig>
<Dir>out</Dir>
<Bits>3</Bits>
<Attribute>address</Attribute>
</RtlPorts>
<RtlPorts>
<name>buf_2_ce0</name>
<Object>buf_2</Object>
<Type>array</Type>
<Scope></Scope>
<IOProtocol>ap_memory</IOProtocol>
<IOConfig></IOConfig>
<Dir>out</Dir>
<Bits>1</Bits>
<Attribute>control</Attribute>
</RtlPorts>
<RtlPorts>
<name>buf_2_we0</name>
<Object>buf_2</Object>
<Type>array</Type>
<Scope></Scope>
<IOProtocol>ap_memory</IOProtocol>
<IOConfig></IOConfig>
<Dir>out</Dir>
<Bits>1</Bits>
<Attribute>control</Attribute>
</RtlPorts>
<RtlPorts>
<name>buf_2_d0</name>
<Object>buf_2</Object>
<Type>array</Type>
<Scope></Scope>
<IOProtocol>ap_memory</IOProtocol>
<IOConfig></IOConfig>
<Dir>out</Dir>
<Bits>16</Bits>
<Attribute>data</Attribute>
</RtlPorts>
<RtlPorts>
<name>buf_3_address0</name>
<Object>buf_3</Object>
<Type>array</Type>
<Scope></Scope>
<IOProtocol>ap_memory</IOProtocol>
<IOConfig></IOConfig>
<Dir>out</Dir>
<Bits>3</Bits>
<Attribute>address</Attribute>
</RtlPorts>
<RtlPorts>
<name>buf_3_ce0</name>
<Object>buf_3</Object>
<Type>array</Type>
<Scope></Scope>
<IOProtocol>ap_memory</IOProtocol>
<IOConfig></IOConfig>
<Dir>out</Dir>
<Bits>1</Bits>
<Attribute>control</Attribute>
</RtlPorts>
<RtlPorts>
<name>buf_3_we0</name>
<Object>buf_3</Object>
<Type>array</Type>
<Scope></Scope>
<IOProtocol>ap_memory</IOProtocol>
<IOConfig></IOConfig>
<Dir>out</Dir>
<Bits>1</Bits>
<Attribute>control</Attribute>
</RtlPorts>
<RtlPorts>
<name>buf_3_d0</name>
<Object>buf_3</Object>
<Type>array</Type>
<Scope></Scope>
<IOProtocol>ap_memory</IOProtocol>
<IOConfig></IOConfig>
<Dir>out</Dir>
<Bits>16</Bits>
<Attribute>data</Attribute>
</RtlPorts>
<RtlPorts>
<name>buf_4_address0</name>
<Object>buf_4</Object>
<Type>array</Type>
<Scope></Scope>
<IOProtocol>ap_memory</IOProtocol>
<IOConfig></IOConfig>
<Dir>out</Dir>
<Bits>3</Bits>
<Attribute>address</Attribute>
</RtlPorts>
<RtlPorts>
<name>buf_4_ce0</name>
<Object>buf_4</Object>
<Type>array</Type>
<Scope></Scope>
<IOProtocol>ap_memory</IOProtocol>
<IOConfig></IOConfig>
<Dir>out</Dir>
<Bits>1</Bits>
<Attribute>control</Attribute>
</RtlPorts>
<RtlPorts>
<name>buf_4_we0</name>
<Object>buf_4</Object>
<Type>array</Type>
<Scope></Scope>
<IOProtocol>ap_memory</IOProtocol>
<IOConfig></IOConfig>
<Dir>out</Dir>
<Bits>1</Bits>
<Attribute>control</Attribute>
</RtlPorts>
<RtlPorts>
<name>buf_4_d0</name>
<Object>buf_4</Object>
<Type>array</Type>
<Scope></Scope>
<IOProtocol>ap_memory</IOProtocol>
<IOConfig></IOConfig>
<Dir>out</Dir>
<Bits>16</Bits>
<Attribute>data</Attribute>
</RtlPorts>
<RtlPorts>
<name>buf_5_address0</name>
<Object>buf_5</Object>
<Type>array</Type>
<Scope></Scope>
<IOProtocol>ap_memory</IOProtocol>
<IOConfig></IOConfig>
<Dir>out</Dir>
<Bits>3</Bits>
<Attribute>address</Attribute>
</RtlPorts>
<RtlPorts>
<name>buf_5_ce0</name>
<Object>buf_5</Object>
<Type>array</Type>
<Scope></Scope>
<IOProtocol>ap_memory</IOProtocol>
<IOConfig></IOConfig>
<Dir>out</Dir>
<Bits>1</Bits>
<Attribute>control</Attribute>
</RtlPorts>
<RtlPorts>
<name>buf_5_we0</name>
<Object>buf_5</Object>
<Type>array</Type>
<Scope></Scope>
<IOProtocol>ap_memory</IOProtocol>
<IOConfig></IOConfig>
<Dir>out</Dir>
<Bits>1</Bits>
<Attribute>control</Attribute>
</RtlPorts>
<RtlPorts>
<name>buf_5_d0</name>
<Object>buf_5</Object>
<Type>array</Type>
<Scope></Scope>
<IOProtocol>ap_memory</IOProtocol>
<IOConfig></IOConfig>
<Dir>out</Dir>
<Bits>16</Bits>
<Attribute>data</Attribute>
</RtlPorts>
<RtlPorts>
<name>buf_6_address0</name>
<Object>buf_6</Object>
<Type>array</Type>
<Scope></Scope>
<IOProtocol>ap_memory</IOProtocol>
<IOConfig></IOConfig>
<Dir>out</Dir>
<Bits>3</Bits>
<Attribute>address</Attribute>
</RtlPorts>
<RtlPorts>
<name>buf_6_ce0</name>
<Object>buf_6</Object>
<Type>array</Type>
<Scope></Scope>
<IOProtocol>ap_memory</IOProtocol>
<IOConfig></IOConfig>
<Dir>out</Dir>
<Bits>1</Bits>
<Attribute>control</Attribute>
</RtlPorts>
<RtlPorts>
<name>buf_6_we0</name>
<Object>buf_6</Object>
<Type>array</Type>
<Scope></Scope>
<IOProtocol>ap_memory</IOProtocol>
<IOConfig></IOConfig>
<Dir>out</Dir>
<Bits>1</Bits>
<Attribute>control</Attribute>
</RtlPorts>
<RtlPorts>
<name>buf_6_d0</name>
<Object>buf_6</Object>
<Type>array</Type>
<Scope></Scope>
<IOProtocol>ap_memory</IOProtocol>
<IOConfig></IOConfig>
<Dir>out</Dir>
<Bits>16</Bits>
<Attribute>data</Attribute>
</RtlPorts>
<RtlPorts>
<name>buf_7_address0</name>
<Object>buf_7</Object>
<Type>array</Type>
<Scope></Scope>
<IOProtocol>ap_memory</IOProtocol>
<IOConfig></IOConfig>
<Dir>out</Dir>
<Bits>3</Bits>
<Attribute>address</Attribute>
</RtlPorts>
<RtlPorts>
<name>buf_7_ce0</name>
<Object>buf_7</Object>
<Type>array</Type>
<Scope></Scope>
<IOProtocol>ap_memory</IOProtocol>
<IOConfig></IOConfig>
<Dir>out</Dir>
<Bits>1</Bits>
<Attribute>control</Attribute>
</RtlPorts>
<RtlPorts>
<name>buf_7_we0</name>
<Object>buf_7</Object>
<Type>array</Type>
<Scope></Scope>
<IOProtocol>ap_memory</IOProtocol>
<IOConfig></IOConfig>
<Dir>out</Dir>
<Bits>1</Bits>
<Attribute>control</Attribute>
</RtlPorts>
<RtlPorts>
<name>buf_7_d0</name>
<Object>buf_7</Object>
<Type>array</Type>
<Scope></Scope>
<IOProtocol>ap_memory</IOProtocol>
<IOConfig></IOConfig>
<Dir>out</Dir>
<Bits>16</Bits>
<Attribute>data</Attribute>
</RtlPorts>
</InterfaceSummary>
</Module>
<Module>
<Name>Loop_Row_DCT_Loop_proc</Name>
<Loops>
<Row_DCT_Loop_DCT_Outer_Loop></Row_DCT_Loop_DCT_Outer_Loop>
</Loops>
<PerformanceEstimates>
<SummaryOfTimingAnalysis>
<TargetClockPeriod>10.00</TargetClockPeriod>
<ClockUncertainty>2.70</ClockUncertainty>
<EstimatedClockPeriod>6.669</EstimatedClockPeriod>
</SummaryOfTimingAnalysis>
<SummaryOfOverallLatency>
<Best-caseLatency>72</Best-caseLatency>
<Average-caseLatency>72</Average-caseLatency>
<Worst-caseLatency>72</Worst-caseLatency>
<Best-caseRealTimeLatency>0.720 us</Best-caseRealTimeLatency>
<Average-caseRealTimeLatency>0.720 us</Average-caseRealTimeLatency>
<Worst-caseRealTimeLatency>0.720 us</Worst-caseRealTimeLatency>
<PipelineInitiationInterval>64</PipelineInitiationInterval>
<PipelineType>loop auto-rewind stp (delay=0 clock cycles(s))</PipelineType>
</SummaryOfOverallLatency>
<SummaryOfLoopLatency>
<Row_DCT_Loop_DCT_Outer_Loop>
<Name>Row_DCT_Loop_DCT_Outer_Loop</Name>
<Slack>7.30</Slack>
<TripCount>64</TripCount>
<Latency>70</Latency>
<AbsoluteTimeLatency>0.700 us</AbsoluteTimeLatency>
<PipelineII>1</PipelineII>
<PipelineDepth>8</PipelineDepth>
<PipelineType>yes</PipelineType>
<InstanceList>
</InstanceList>
</Row_DCT_Loop_DCT_Outer_Loop>
</SummaryOfLoopLatency>
<SummaryOfViolations>
<IssueType>-</IssueType>
<ViolationType>-</ViolationType>
<SourceLocation>E:/robot/project/xilinx_fpga_class/hls/lab3/dct.c:39~E:/robot/project/xilinx_fpga_class/hls/lab3/dct.c:62</SourceLocation>
<SummaryOfLoopViolations>
<Row_DCT_Loop_DCT_Outer_Loop>
<Name>Row_DCT_Loop_DCT_Outer_Loop</Name>
<IssueType>-</IssueType>
<ViolationType>-</ViolationType>
<SourceLocation>E:/robot/project/xilinx_fpga_class/hls/lab3/dct.c:39~E:/robot/project/xilinx_fpga_class/hls/lab3/dct.c:62</SourceLocation>
</Row_DCT_Loop_DCT_Outer_Loop>
</SummaryOfLoopViolations>
</SummaryOfViolations>
</PerformanceEstimates>
<AreaEstimates>
<Resources>
<BRAM_18K>0</BRAM_18K>
<AVAIL_BRAM>280</AVAIL_BRAM>
<UTIL_BRAM>0</UTIL_BRAM>
<DSP>8</DSP>
<AVAIL_DSP>220</AVAIL_DSP>
<UTIL_DSP>3</UTIL_DSP>
<FF>686</FF>
<AVAIL_FF>106400</AVAIL_FF>
<UTIL_FF>~0</UTIL_FF>
<LUT>370</LUT>
<AVAIL_LUT>53200</AVAIL_LUT>
<UTIL_LUT>~0</UTIL_LUT>
<URAM>0</URAM>
<AVAIL_URAM>0</AVAIL_URAM>
<UTIL_URAM>0</UTIL_URAM>
</Resources>
</AreaEstimates>
<InterfaceSummary>
<RtlPorts>
<name>ap_clk</name>
<Object>Loop_Row_DCT_Loop_proc</Object>
<Type>return value</Type>
<Scope></Scope>
<IOProtocol>ap_ctrl_hs</IOProtocol>
<IOConfig></IOConfig>
<Dir>in</Dir>
<Bits>1</Bits>
<Attribute>control</Attribute>
</RtlPorts>
<RtlPorts>
<name>ap_rst</name>
<Object>Loop_Row_DCT_Loop_proc</Object>
<Type>return value</Type>
<Scope></Scope>
<IOProtocol>ap_ctrl_hs</IOProtocol>
<IOConfig></IOConfig>
<Dir>in</Dir>
<Bits>1</Bits>
<Attribute>control</Attribute>
</RtlPorts>
<RtlPorts>
<name>ap_start</name>
<Object>Loop_Row_DCT_Loop_proc</Object>
<Type>return value</Type>
<Scope></Scope>
<IOProtocol>ap_ctrl_hs</IOProtocol>
<IOConfig></IOConfig>
<Dir>in</Dir>
<Bits>1</Bits>
<Attribute>control</Attribute>
</RtlPorts>
<RtlPorts>
<name>ap_done</name>
<Object>Loop_Row_DCT_Loop_proc</Object>
<Type>return value</Type>
<Scope></Scope>
<IOProtocol>ap_ctrl_hs</IOProtocol>
<IOConfig></IOConfig>
<Dir>out</Dir>
<Bits>1</Bits>
<Attribute>control</Attribute>
</RtlPorts>
<RtlPorts>
<name>ap_continue</name>
<Object>Loop_Row_DCT_Loop_proc</Object>
<Type>return value</Type>
<Scope></Scope>
<IOProtocol>ap_ctrl_hs</IOProtocol>
<IOConfig></IOConfig>
<Dir>in</Dir>
<Bits>1</Bits>
<Attribute>control</Attribute>
</RtlPorts>
<RtlPorts>
<name>ap_idle</name>
<Object>Loop_Row_DCT_Loop_proc</Object>
<Type>return value</Type>
<Scope></Scope>
<IOProtocol>ap_ctrl_hs</IOProtocol>
<IOConfig></IOConfig>
<Dir>out</Dir>
<Bits>1</Bits>
<Attribute>control</Attribute>
</RtlPorts>
<RtlPorts>
<name>ap_ready</name>
<Object>Loop_Row_DCT_Loop_proc</Object>
<Type>return value</Type>
<Scope></Scope>
<IOProtocol>ap_ctrl_hs</IOProtocol>
<IOConfig></IOConfig>
<Dir>out</Dir>
<Bits>1</Bits>
<Attribute>control</Attribute>
</RtlPorts>
<RtlPorts>
<name>buf_2d_in_0_address0</name>
<Object>buf_2d_in_0</Object>
<Type>array</Type>
<Scope></Scope>
<IOProtocol>ap_memory</IOProtocol>
<IOConfig></IOConfig>
<Dir>out</Dir>
<Bits>3</Bits>
<Attribute>address</Attribute>
</RtlPorts>
<RtlPorts>
<name>buf_2d_in_0_ce0</name>
<Object>buf_2d_in_0</Object>
<Type>array</Type>
<Scope></Scope>
<IOProtocol>ap_memory</IOProtocol>
<IOConfig></IOConfig>
<Dir>out</Dir>
<Bits>1</Bits>
<Attribute>control</Attribute>
</RtlPorts>
<RtlPorts>
<name>buf_2d_in_0_q0</name>
<Object>buf_2d_in_0</Object>
<Type>array</Type>
<Scope></Scope>
<IOProtocol>ap_memory</IOProtocol>
<IOConfig></IOConfig>
<Dir>in</Dir>
<Bits>16</Bits>
<Attribute>data</Attribute>
</RtlPorts>
<RtlPorts>
<name>buf_2d_in_1_address0</name>
<Object>buf_2d_in_1</Object>
<Type>array</Type>
<Scope></Scope>
<IOProtocol>ap_memory</IOProtocol>
<IOConfig></IOConfig>
<Dir>out</Dir>
<Bits>3</Bits>
<Attribute>address</Attribute>
</RtlPorts>
<RtlPorts>
<name>buf_2d_in_1_ce0</name>
<Object>buf_2d_in_1</Object>
<Type>array</Type>
<Scope></Scope>
<IOProtocol>ap_memory</IOProtocol>
<IOConfig></IOConfig>
<Dir>out</Dir>
<Bits>1</Bits>
<Attribute>control</Attribute>
</RtlPorts>
<RtlPorts>
<name>buf_2d_in_1_q0</name>
<Object>buf_2d_in_1</Object>
<Type>array</Type>
<Scope></Scope>
<IOProtocol>ap_memory</IOProtocol>
<IOConfig></IOConfig>
<Dir>in</Dir>
<Bits>16</Bits>
<Attribute>data</Attribute>
</RtlPorts>
<RtlPorts>
<name>buf_2d_in_2_address0</name>
<Object>buf_2d_in_2</Object>
<Type>array</Type>
<Scope></Scope>
<IOProtocol>ap_memory</IOProtocol>
<IOConfig></IOConfig>
<Dir>out</Dir>
<Bits>3</Bits>
<Attribute>address</Attribute>
</RtlPorts>
<RtlPorts>
<name>buf_2d_in_2_ce0</name>
<Object>buf_2d_in_2</Object>
<Type>array</Type>
<Scope></Scope>
<IOProtocol>ap_memory</IOProtocol>
<IOConfig></IOConfig>
<Dir>out</Dir>
<Bits>1</Bits>
<Attribute>control</Attribute>
</RtlPorts>
<RtlPorts>
<name>buf_2d_in_2_q0</name>
<Object>buf_2d_in_2</Object>
<Type>array</Type>
<Scope></Scope>
<IOProtocol>ap_memory</IOProtocol>
<IOConfig></IOConfig>
<Dir>in</Dir>
<Bits>16</Bits>
<Attribute>data</Attribute>
</RtlPorts>
<RtlPorts>
<name>buf_2d_in_3_address0</name>
<Object>buf_2d_in_3</Object>
<Type>array</Type>
<Scope></Scope>
<IOProtocol>ap_memory</IOProtocol>
<IOConfig></IOConfig>
<Dir>out</Dir>
<Bits>3</Bits>
<Attribute>address</Attribute>
</RtlPorts>
<RtlPorts>
<name>buf_2d_in_3_ce0</name>
<Object>buf_2d_in_3</Object>
<Type>array</Type>
<Scope></Scope>
<IOProtocol>ap_memory</IOProtocol>
<IOConfig></IOConfig>
<Dir>out</Dir>
<Bits>1</Bits>
<Attribute>control</Attribute>
</RtlPorts>
<RtlPorts>
<name>buf_2d_in_3_q0</name>
<Object>buf_2d_in_3</Object>
<Type>array</Type>
<Scope></Scope>
<IOProtocol>ap_memory</IOProtocol>
<IOConfig></IOConfig>
<Dir>in</Dir>
<Bits>16</Bits>
<Attribute>data</Attribute>
</RtlPorts>
<RtlPorts>
<name>buf_2d_in_4_address0</name>
<Object>buf_2d_in_4</Object>
<Type>array</Type>
<Scope></Scope>
<IOProtocol>ap_memory</IOProtocol>
<IOConfig></IOConfig>
<Dir>out</Dir>
<Bits>3</Bits>
<Attribute>address</Attribute>
</RtlPorts>
<RtlPorts>
<name>buf_2d_in_4_ce0</name>
<Object>buf_2d_in_4</Object>
<Type>array</Type>
<Scope></Scope>
<IOProtocol>ap_memory</IOProtocol>
<IOConfig></IOConfig>
<Dir>out</Dir>
<Bits>1</Bits>
<Attribute>control</Attribute>
</RtlPorts>
<RtlPorts>
<name>buf_2d_in_4_q0</name>
<Object>buf_2d_in_4</Object>
<Type>array</Type>
<Scope></Scope>
<IOProtocol>ap_memory</IOProtocol>
<IOConfig></IOConfig>
<Dir>in</Dir>
<Bits>16</Bits>
<Attribute>data</Attribute>
</RtlPorts>
<RtlPorts>
<name>buf_2d_in_5_address0</name>
<Object>buf_2d_in_5</Object>
<Type>array</Type>
<Scope></Scope>
<IOProtocol>ap_memory</IOProtocol>
<IOConfig></IOConfig>
<Dir>out</Dir>
<Bits>3</Bits>
<Attribute>address</Attribute>
</RtlPorts>
<RtlPorts>
<name>buf_2d_in_5_ce0</name>
<Object>buf_2d_in_5</Object>
<Type>array</Type>
<Scope></Scope>
<IOProtocol>ap_memory</IOProtocol>
<IOConfig></IOConfig>
<Dir>out</Dir>
<Bits>1</Bits>
<Attribute>control</Attribute>
</RtlPorts>
<RtlPorts>
<name>buf_2d_in_5_q0</name>
<Object>buf_2d_in_5</Object>
<Type>array</Type>
<Scope></Scope>
<IOProtocol>ap_memory</IOProtocol>
<IOConfig></IOConfig>
<Dir>in</Dir>
<Bits>16</Bits>
<Attribute>data</Attribute>
</RtlPorts>
<RtlPorts>
<name>buf_2d_in_6_address0</name>
<Object>buf_2d_in_6</Object>
<Type>array</Type>
<Scope></Scope>
<IOProtocol>ap_memory</IOProtocol>
<IOConfig></IOConfig>
<Dir>out</Dir>
<Bits>3</Bits>
<Attribute>address</Attribute>
</RtlPorts>
<RtlPorts>
<name>buf_2d_in_6_ce0</name>
<Object>buf_2d_in_6</Object>
<Type>array</Type>
<Scope></Scope>
<IOProtocol>ap_memory</IOProtocol>
<IOConfig></IOConfig>
<Dir>out</Dir>
<Bits>1</Bits>
<Attribute>control</Attribute>
</RtlPorts>
<RtlPorts>
<name>buf_2d_in_6_q0</name>
<Object>buf_2d_in_6</Object>
<Type>array</Type>
<Scope></Scope>
<IOProtocol>ap_memory</IOProtocol>
<IOConfig></IOConfig>
<Dir>in</Dir>
<Bits>16</Bits>
<Attribute>data</Attribute>
</RtlPorts>
<RtlPorts>
<name>buf_2d_in_7_address0</name>
<Object>buf_2d_in_7</Object>
<Type>array</Type>
<Scope></Scope>
<IOProtocol>ap_memory</IOProtocol>
<IOConfig></IOConfig>
<Dir>out</Dir>
<Bits>3</Bits>
<Attribute>address</Attribute>
</RtlPorts>
<RtlPorts>
<name>buf_2d_in_7_ce0</name>
<Object>buf_2d_in_7</Object>
<Type>array</Type>
<Scope></Scope>
<IOProtocol>ap_memory</IOProtocol>
<IOConfig></IOConfig>
<Dir>out</Dir>
<Bits>1</Bits>
<Attribute>control</Attribute>
</RtlPorts>
<RtlPorts>
<name>buf_2d_in_7_q0</name>
<Object>buf_2d_in_7</Object>
<Type>array</Type>
<Scope></Scope>
<IOProtocol>ap_memory</IOProtocol>
<IOConfig></IOConfig>
<Dir>in</Dir>
<Bits>16</Bits>
<Attribute>data</Attribute>
</RtlPorts>
<RtlPorts>
<name>row_outbuf_i_address0</name>
<Object>row_outbuf_i</Object>
<Type>array</Type>
<Scope></Scope>
<IOProtocol>ap_memory</IOProtocol>
<IOConfig></IOConfig>
<Dir>out</Dir>
<Bits>6</Bits>
<Attribute>address</Attribute>
</RtlPorts>
<RtlPorts>
<name>row_outbuf_i_ce0</name>
<Object>row_outbuf_i</Object>
<Type>array</Type>
<Scope></Scope>
<IOProtocol>ap_memory</IOProtocol>
<IOConfig></IOConfig>
<Dir>out</Dir>
<Bits>1</Bits>
<Attribute>control</Attribute>
</RtlPorts>
<RtlPorts>
<name>row_outbuf_i_we0</name>
<Object>row_outbuf_i</Object>
<Type>array</Type>
<Scope></Scope>
<IOProtocol>ap_memory</IOProtocol>
<IOConfig></IOConfig>
<Dir>out</Dir>
<Bits>1</Bits>
<Attribute>control</Attribute>
</RtlPorts>
<RtlPorts>
<name>row_outbuf_i_d0</name>
<Object>row_outbuf_i</Object>
<Type>array</Type>
<Scope></Scope>
<IOProtocol>ap_memory</IOProtocol>
<IOConfig></IOConfig>
<Dir>out</Dir>
<Bits>16</Bits>
<Attribute>data</Attribute>
</RtlPorts>
</InterfaceSummary>
</Module>
<Module>
<Name>Loop_Xpose_Row_Outer_Loop_proc</Name>
<Loops>
<Xpose_Row_Outer_Loop_Xpose_Row_Inner_Loop></Xpose_Row_Outer_Loop_Xpose_Row_Inner_Loop>
</Loops>
<PerformanceEstimates>
<SummaryOfTimingAnalysis>
<TargetClockPeriod>10.00</TargetClockPeriod>
<ClockUncertainty>2.70</ClockUncertainty>
<EstimatedClockPeriod>6.082</EstimatedClockPeriod>
</SummaryOfTimingAnalysis>
<SummaryOfOverallLatency>
<Best-caseLatency>67</Best-caseLatency>
<Average-caseLatency>67</Average-caseLatency>
<Worst-caseLatency>67</Worst-caseLatency>
<Best-caseRealTimeLatency>0.670 us</Best-caseRealTimeLatency>
<Average-caseRealTimeLatency>0.670 us</Average-caseRealTimeLatency>
<Worst-caseRealTimeLatency>0.670 us</Worst-caseRealTimeLatency>
<PipelineInitiationInterval>65</PipelineInitiationInterval>
<PipelineType>loop auto-rewind stp (delay=1 clock cycles(s))</PipelineType>
</SummaryOfOverallLatency>
<SummaryOfLoopLatency>
<Xpose_Row_Outer_Loop_Xpose_Row_Inner_Loop>
<Name>Xpose_Row_Outer_Loop_Xpose_Row_Inner_Loop</Name>
<Slack>7.30</Slack>
<TripCount>64</TripCount>
<Latency>65</Latency>
<AbsoluteTimeLatency>0.650 us</AbsoluteTimeLatency>
<PipelineII>1</PipelineII>
<PipelineDepth>3</PipelineDepth>
<PipelineType>yes</PipelineType>
<InstanceList>
</InstanceList>
</Xpose_Row_Outer_Loop_Xpose_Row_Inner_Loop>
</SummaryOfLoopLatency>
<SummaryOfViolations>
<IssueType>-</IssueType>
<ViolationType>-</ViolationType>
<SourceLocation>E:/robot/project/xilinx_fpga_class/hls/lab3/dct.c:69</SourceLocation>
<SummaryOfLoopViolations>
<Xpose_Row_Outer_Loop_Xpose_Row_Inner_Loop>
<Name>Xpose_Row_Outer_Loop_Xpose_Row_Inner_Loop</Name>
<IssueType>-</IssueType>
<ViolationType>-</ViolationType>
<SourceLocation>E:/robot/project/xilinx_fpga_class/hls/lab3/dct.c:69</SourceLocation>
</Xpose_Row_Outer_Loop_Xpose_Row_Inner_Loop>
</SummaryOfLoopViolations>
</SummaryOfViolations>
</PerformanceEstimates>
<AreaEstimates>
<Resources>
<FF>37</FF>
<AVAIL_FF>106400</AVAIL_FF>
<UTIL_FF>~0</UTIL_FF>
<LUT>178</LUT>
<AVAIL_LUT>53200</AVAIL_LUT>
<UTIL_LUT>~0</UTIL_LUT>
<BRAM_18K>0</BRAM_18K>
<AVAIL_BRAM>280</AVAIL_BRAM>
<UTIL_BRAM>0</UTIL_BRAM>
<DSP>0</DSP>
<AVAIL_DSP>220</AVAIL_DSP>
<UTIL_DSP>0</UTIL_DSP>
<URAM>0</URAM>
<AVAIL_URAM>0</AVAIL_URAM>
<UTIL_URAM>0</UTIL_URAM>
</Resources>
</AreaEstimates>
<InterfaceSummary>
<RtlPorts>
<name>ap_clk</name>
<Object>Loop_Xpose_Row_Outer_Loop_proc</Object>
<Type>return value</Type>
<Scope></Scope>
<IOProtocol>ap_ctrl_hs</IOProtocol>
<IOConfig></IOConfig>
<Dir>in</Dir>
<Bits>1</Bits>
<Attribute>control</Attribute>
</RtlPorts>
<RtlPorts>
<name>ap_rst</name>
<Object>Loop_Xpose_Row_Outer_Loop_proc</Object>
<Type>return value</Type>
<Scope></Scope>
<IOProtocol>ap_ctrl_hs</IOProtocol>
<IOConfig></IOConfig>
<Dir>in</Dir>
<Bits>1</Bits>
<Attribute>control</Attribute>
</RtlPorts>
<RtlPorts>
<name>ap_start</name>
<Object>Loop_Xpose_Row_Outer_Loop_proc</Object>
<Type>return value</Type>
<Scope></Scope>
<IOProtocol>ap_ctrl_hs</IOProtocol>
<IOConfig></IOConfig>
<Dir>in</Dir>
<Bits>1</Bits>
<Attribute>control</Attribute>
</RtlPorts>
<RtlPorts>
<name>ap_done</name>
<Object>Loop_Xpose_Row_Outer_Loop_proc</Object>
<Type>return value</Type>
<Scope></Scope>
<IOProtocol>ap_ctrl_hs</IOProtocol>
<IOConfig></IOConfig>
<Dir>out</Dir>
<Bits>1</Bits>
<Attribute>control</Attribute>
</RtlPorts>
<RtlPorts>
<name>ap_continue</name>
<Object>Loop_Xpose_Row_Outer_Loop_proc</Object>
<Type>return value</Type>
<Scope></Scope>
<IOProtocol>ap_ctrl_hs</IOProtocol>
<IOConfig></IOConfig>
<Dir>in</Dir>
<Bits>1</Bits>
<Attribute>control</Attribute>
</RtlPorts>
<RtlPorts>
<name>ap_idle</name>
<Object>Loop_Xpose_Row_Outer_Loop_proc</Object>
<Type>return value</Type>
<Scope></Scope>
<IOProtocol>ap_ctrl_hs</IOProtocol>
<IOConfig></IOConfig>
<Dir>out</Dir>
<Bits>1</Bits>
<Attribute>control</Attribute>
</RtlPorts>
<RtlPorts>
<name>ap_ready</name>
<Object>Loop_Xpose_Row_Outer_Loop_proc</Object>
<Type>return value</Type>
<Scope></Scope>
<IOProtocol>ap_ctrl_hs</IOProtocol>
<IOConfig></IOConfig>
<Dir>out</Dir>
<Bits>1</Bits>
<Attribute>control</Attribute>
</RtlPorts>
<RtlPorts>
<name>col_inbuf_i_7_address0</name>
<Object>col_inbuf_i_7</Object>
<Type>array</Type>
<Scope></Scope>
<IOProtocol>ap_memory</IOProtocol>
<IOConfig></IOConfig>
<Dir>out</Dir>
<Bits>3</Bits>
<Attribute>address</Attribute>
</RtlPorts>
<RtlPorts>
<name>col_inbuf_i_7_ce0</name>
<Object>col_inbuf_i_7</Object>
<Type>array</Type>
<Scope></Scope>
<IOProtocol>ap_memory</IOProtocol>
<IOConfig></IOConfig>
<Dir>out</Dir>
<Bits>1</Bits>
<Attribute>control</Attribute>
</RtlPorts>
<RtlPorts>
<name>col_inbuf_i_7_we0</name>
<Object>col_inbuf_i_7</Object>
<Type>array</Type>
<Scope></Scope>
<IOProtocol>ap_memory</IOProtocol>
<IOConfig></IOConfig>
<Dir>out</Dir>
<Bits>1</Bits>
<Attribute>control</Attribute>
</RtlPorts>
<RtlPorts>
<name>col_inbuf_i_7_d0</name>
<Object>col_inbuf_i_7</Object>
<Type>array</Type>
<Scope></Scope>
<IOProtocol>ap_memory</IOProtocol>
<IOConfig></IOConfig>
<Dir>out</Dir>
<Bits>16</Bits>
<Attribute>data</Attribute>
</RtlPorts>
<RtlPorts>
<name>col_inbuf_i_6_address0</name>
<Object>col_inbuf_i_6</Object>
<Type>array</Type>
<Scope></Scope>
<IOProtocol>ap_memory</IOProtocol>
<IOConfig></IOConfig>
<Dir>out</Dir>
<Bits>3</Bits>
<Attribute>address</Attribute>
</RtlPorts>
<RtlPorts>
<name>col_inbuf_i_6_ce0</name>
<Object>col_inbuf_i_6</Object>
<Type>array</Type>
<Scope></Scope>
<IOProtocol>ap_memory</IOProtocol>
<IOConfig></IOConfig>
<Dir>out</Dir>
<Bits>1</Bits>
<Attribute>control</Attribute>
</RtlPorts>
<RtlPorts>
<name>col_inbuf_i_6_we0</name>
<Object>col_inbuf_i_6</Object>
<Type>array</Type>
<Scope></Scope>
<IOProtocol>ap_memory</IOProtocol>
<IOConfig></IOConfig>
<Dir>out</Dir>
<Bits>1</Bits>
<Attribute>control</Attribute>
</RtlPorts>
<RtlPorts>
<name>col_inbuf_i_6_d0</name>
<Object>col_inbuf_i_6</Object>
<Type>array</Type>
<Scope></Scope>
<IOProtocol>ap_memory</IOProtocol>
<IOConfig></IOConfig>
<Dir>out</Dir>
<Bits>16</Bits>
<Attribute>data</Attribute>
</RtlPorts>
<RtlPorts>
<name>col_inbuf_i_5_address0</name>
<Object>col_inbuf_i_5</Object>
<Type>array</Type>
<Scope></Scope>
<IOProtocol>ap_memory</IOProtocol>
<IOConfig></IOConfig>
<Dir>out</Dir>
<Bits>3</Bits>
<Attribute>address</Attribute>
</RtlPorts>
<RtlPorts>
<name>col_inbuf_i_5_ce0</name>
<Object>col_inbuf_i_5</Object>
<Type>array</Type>
<Scope></Scope>
<IOProtocol>ap_memory</IOProtocol>
<IOConfig></IOConfig>
<Dir>out</Dir>
<Bits>1</Bits>
<Attribute>control</Attribute>
</RtlPorts>
<RtlPorts>
<name>col_inbuf_i_5_we0</name>
<Object>col_inbuf_i_5</Object>
<Type>array</Type>
<Scope></Scope>
<IOProtocol>ap_memory</IOProtocol>
<IOConfig></IOConfig>
<Dir>out</Dir>
<Bits>1</Bits>
<Attribute>control</Attribute>
</RtlPorts>
<RtlPorts>
<name>col_inbuf_i_5_d0</name>
<Object>col_inbuf_i_5</Object>
<Type>array</Type>
<Scope></Scope>
<IOProtocol>ap_memory</IOProtocol>
<IOConfig></IOConfig>
<Dir>out</Dir>
<Bits>16</Bits>
<Attribute>data</Attribute>
</RtlPorts>
<RtlPorts>
<name>col_inbuf_i_4_address0</name>
<Object>col_inbuf_i_4</Object>
<Type>array</Type>
<Scope></Scope>
<IOProtocol>ap_memory</IOProtocol>
<IOConfig></IOConfig>
<Dir>out</Dir>
<Bits>3</Bits>
<Attribute>address</Attribute>
</RtlPorts>
<RtlPorts>
<name>col_inbuf_i_4_ce0</name>
<Object>col_inbuf_i_4</Object>
<Type>array</Type>
<Scope></Scope>
<IOProtocol>ap_memory</IOProtocol>
<IOConfig></IOConfig>
<Dir>out</Dir>
<Bits>1</Bits>
<Attribute>control</Attribute>
</RtlPorts>
<RtlPorts>
<name>col_inbuf_i_4_we0</name>
<Object>col_inbuf_i_4</Object>
<Type>array</Type>
<Scope></Scope>
<IOProtocol>ap_memory</IOProtocol>
<IOConfig></IOConfig>
<Dir>out</Dir>
<Bits>1</Bits>
<Attribute>control</Attribute>
</RtlPorts>
<RtlPorts>
<name>col_inbuf_i_4_d0</name>
<Object>col_inbuf_i_4</Object>
<Type>array</Type>
<Scope></Scope>
<IOProtocol>ap_memory</IOProtocol>
<IOConfig></IOConfig>
<Dir>out</Dir>
<Bits>16</Bits>
<Attribute>data</Attribute>
</RtlPorts>
<RtlPorts>
<name>col_inbuf_i_3_address0</name>
<Object>col_inbuf_i_3</Object>
<Type>array</Type>
<Scope></Scope>
<IOProtocol>ap_memory</IOProtocol>
<IOConfig></IOConfig>
<Dir>out</Dir>
<Bits>3</Bits>
<Attribute>address</Attribute>
</RtlPorts>
<RtlPorts>
<name>col_inbuf_i_3_ce0</name>
<Object>col_inbuf_i_3</Object>
<Type>array</Type>
<Scope></Scope>
<IOProtocol>ap_memory</IOProtocol>
<IOConfig></IOConfig>
<Dir>out</Dir>
<Bits>1</Bits>
<Attribute>control</Attribute>
</RtlPorts>
<RtlPorts>
<name>col_inbuf_i_3_we0</name>
<Object>col_inbuf_i_3</Object>
<Type>array</Type>
<Scope></Scope>
<IOProtocol>ap_memory</IOProtocol>
<IOConfig></IOConfig>
<Dir>out</Dir>
<Bits>1</Bits>
<Attribute>control</Attribute>
</RtlPorts>
<RtlPorts>
<name>col_inbuf_i_3_d0</name>
<Object>col_inbuf_i_3</Object>
<Type>array</Type>
<Scope></Scope>
<IOProtocol>ap_memory</IOProtocol>
<IOConfig></IOConfig>
<Dir>out</Dir>
<Bits>16</Bits>
<Attribute>data</Attribute>
</RtlPorts>
<RtlPorts>
<name>col_inbuf_i_2_address0</name>
<Object>col_inbuf_i_2</Object>
<Type>array</Type>
<Scope></Scope>
<IOProtocol>ap_memory</IOProtocol>
<IOConfig></IOConfig>
<Dir>out</Dir>
<Bits>3</Bits>
<Attribute>address</Attribute>
</RtlPorts>
<RtlPorts>
<name>col_inbuf_i_2_ce0</name>
<Object>col_inbuf_i_2</Object>
<Type>array</Type>
<Scope></Scope>
<IOProtocol>ap_memory</IOProtocol>
<IOConfig></IOConfig>
<Dir>out</Dir>
<Bits>1</Bits>
<Attribute>control</Attribute>
</RtlPorts>
<RtlPorts>
<name>col_inbuf_i_2_we0</name>
<Object>col_inbuf_i_2</Object>
<Type>array</Type>
<Scope></Scope>
<IOProtocol>ap_memory</IOProtocol>
<IOConfig></IOConfig>
<Dir>out</Dir>
<Bits>1</Bits>
<Attribute>control</Attribute>
</RtlPorts>
<RtlPorts>
<name>col_inbuf_i_2_d0</name>
<Object>col_inbuf_i_2</Object>
<Type>array</Type>
<Scope></Scope>
<IOProtocol>ap_memory</IOProtocol>
<IOConfig></IOConfig>
<Dir>out</Dir>
<Bits>16</Bits>
<Attribute>data</Attribute>
</RtlPorts>
<RtlPorts>
<name>col_inbuf_i_1_address0</name>
<Object>col_inbuf_i_1</Object>
<Type>array</Type>
<Scope></Scope>
<IOProtocol>ap_memory</IOProtocol>
<IOConfig></IOConfig>
<Dir>out</Dir>
<Bits>3</Bits>
<Attribute>address</Attribute>
</RtlPorts>
<RtlPorts>
<name>col_inbuf_i_1_ce0</name>
<Object>col_inbuf_i_1</Object>
<Type>array</Type>
<Scope></Scope>
<IOProtocol>ap_memory</IOProtocol>
<IOConfig></IOConfig>
<Dir>out</Dir>
<Bits>1</Bits>
<Attribute>control</Attribute>
</RtlPorts>
<RtlPorts>
<name>col_inbuf_i_1_we0</name>
<Object>col_inbuf_i_1</Object>
<Type>array</Type>
<Scope></Scope>
<IOProtocol>ap_memory</IOProtocol>
<IOConfig></IOConfig>
<Dir>out</Dir>
<Bits>1</Bits>
<Attribute>control</Attribute>
</RtlPorts>
<RtlPorts>
<name>col_inbuf_i_1_d0</name>
<Object>col_inbuf_i_1</Object>
<Type>array</Type>
<Scope></Scope>
<IOProtocol>ap_memory</IOProtocol>
<IOConfig></IOConfig>
<Dir>out</Dir>
<Bits>16</Bits>
<Attribute>data</Attribute>
</RtlPorts>
<RtlPorts>
<name>col_inbuf_i_0_address0</name>
<Object>col_inbuf_i_0</Object>
<Type>array</Type>
<Scope></Scope>
<IOProtocol>ap_memory</IOProtocol>
<IOConfig></IOConfig>
<Dir>out</Dir>
<Bits>3</Bits>
<Attribute>address</Attribute>
</RtlPorts>
<RtlPorts>
<name>col_inbuf_i_0_ce0</name>
<Object>col_inbuf_i_0</Object>
<Type>array</Type>
<Scope></Scope>
<IOProtocol>ap_memory</IOProtocol>
<IOConfig></IOConfig>
<Dir>out</Dir>
<Bits>1</Bits>
<Attribute>control</Attribute>
</RtlPorts>
<RtlPorts>
<name>col_inbuf_i_0_we0</name>
<Object>col_inbuf_i_0</Object>
<Type>array</Type>
<Scope></Scope>
<IOProtocol>ap_memory</IOProtocol>
<IOConfig></IOConfig>
<Dir>out</Dir>
<Bits>1</Bits>
<Attribute>control</Attribute>
</RtlPorts>
<RtlPorts>
<name>col_inbuf_i_0_d0</name>
<Object>col_inbuf_i_0</Object>
<Type>array</Type>
<Scope></Scope>
<IOProtocol>ap_memory</IOProtocol>
<IOConfig></IOConfig>
<Dir>out</Dir>
<Bits>16</Bits>
<Attribute>data</Attribute>
</RtlPorts>
<RtlPorts>
<name>row_outbuf_i_address0</name>
<Object>row_outbuf_i</Object>
<Type>array</Type>
<Scope></Scope>
<IOProtocol>ap_memory</IOProtocol>
<IOConfig></IOConfig>
<Dir>out</Dir>
<Bits>6</Bits>
<Attribute>address</Attribute>
</RtlPorts>
<RtlPorts>
<name>row_outbuf_i_ce0</name>
<Object>row_outbuf_i</Object>
<Type>array</Type>
<Scope></Scope>
<IOProtocol>ap_memory</IOProtocol>
<IOConfig></IOConfig>
<Dir>out</Dir>
<Bits>1</Bits>
<Attribute>control</Attribute>
</RtlPorts>
<RtlPorts>
<name>row_outbuf_i_q0</name>
<Object>row_outbuf_i</Object>
<Type>array</Type>
<Scope></Scope>
<IOProtocol>ap_memory</IOProtocol>
<IOConfig></IOConfig>
<Dir>in</Dir>
<Bits>16</Bits>
<Attribute>data</Attribute>
</RtlPorts>
</InterfaceSummary>
</Module>
<Module>
<Name>Loop_Col_DCT_Loop_proc</Name>
<Loops>
<Col_DCT_Loop_DCT_Outer_Loop></Col_DCT_Loop_DCT_Outer_Loop>
</Loops>
<PerformanceEstimates>
<SummaryOfTimingAnalysis>
<TargetClockPeriod>10.00</TargetClockPeriod>
<ClockUncertainty>2.70</ClockUncertainty>
<EstimatedClockPeriod>6.669</EstimatedClockPeriod>
</SummaryOfTimingAnalysis>
<SummaryOfOverallLatency>
<Best-caseLatency>72</Best-caseLatency>
<Average-caseLatency>72</Average-caseLatency>
<Worst-caseLatency>72</Worst-caseLatency>
<Best-caseRealTimeLatency>0.720 us</Best-caseRealTimeLatency>
<Average-caseRealTimeLatency>0.720 us</Average-caseRealTimeLatency>
<Worst-caseRealTimeLatency>0.720 us</Worst-caseRealTimeLatency>
<PipelineInitiationInterval>64</PipelineInitiationInterval>
<PipelineType>loop auto-rewind stp (delay=0 clock cycles(s))</PipelineType>
</SummaryOfOverallLatency>
<SummaryOfLoopLatency>
<Col_DCT_Loop_DCT_Outer_Loop>
<Name>Col_DCT_Loop_DCT_Outer_Loop</Name>
<Slack>7.30</Slack>
<TripCount>64</TripCount>
<Latency>70</Latency>
<AbsoluteTimeLatency>0.700 us</AbsoluteTimeLatency>
<PipelineII>1</PipelineII>
<PipelineDepth>8</PipelineDepth>
<PipelineType>yes</PipelineType>
<InstanceList>
</InstanceList>
</Col_DCT_Loop_DCT_Outer_Loop>
</SummaryOfLoopLatency>
<SummaryOfViolations>
<IssueType>-</IssueType>
<ViolationType>-</ViolationType>
<SourceLocation>E:/robot/project/xilinx_fpga_class/hls/lab3/dct.c:39~E:/robot/project/xilinx_fpga_class/hls/lab3/dct.c:76</SourceLocation>
<SummaryOfLoopViolations>
<Col_DCT_Loop_DCT_Outer_Loop>
<Name>Col_DCT_Loop_DCT_Outer_Loop</Name>
<IssueType>-</IssueType>
<ViolationType>-</ViolationType>
<SourceLocation>E:/robot/project/xilinx_fpga_class/hls/lab3/dct.c:39~E:/robot/project/xilinx_fpga_class/hls/lab3/dct.c:76</SourceLocation>
</Col_DCT_Loop_DCT_Outer_Loop>
</SummaryOfLoopViolations>
</SummaryOfViolations>
</PerformanceEstimates>
<AreaEstimates>
<Resources>
<BRAM_18K>0</BRAM_18K>
<AVAIL_BRAM>280</AVAIL_BRAM>
<UTIL_BRAM>0</UTIL_BRAM>
<DSP>8</DSP>
<AVAIL_DSP>220</AVAIL_DSP>
<UTIL_DSP>3</UTIL_DSP>
<FF>686</FF>
<AVAIL_FF>106400</AVAIL_FF>
<UTIL_FF>~0</UTIL_FF>
<LUT>370</LUT>
<AVAIL_LUT>53200</AVAIL_LUT>
<UTIL_LUT>~0</UTIL_LUT>
<URAM>0</URAM>
<AVAIL_URAM>0</AVAIL_URAM>
<UTIL_URAM>0</UTIL_URAM>
</Resources>
</AreaEstimates>
<InterfaceSummary>
<RtlPorts>
<name>ap_clk</name>
<Object>Loop_Col_DCT_Loop_proc</Object>
<Type>return value</Type>
<Scope></Scope>
<IOProtocol>ap_ctrl_hs</IOProtocol>
<IOConfig></IOConfig>
<Dir>in</Dir>
<Bits>1</Bits>
<Attribute>control</Attribute>
</RtlPorts>
<RtlPorts>
<name>ap_rst</name>
<Object>Loop_Col_DCT_Loop_proc</Object>
<Type>return value</Type>
<Scope></Scope>
<IOProtocol>ap_ctrl_hs</IOProtocol>
<IOConfig></IOConfig>
<Dir>in</Dir>
<Bits>1</Bits>
<Attribute>control</Attribute>
</RtlPorts>
<RtlPorts>
<name>ap_start</name>
<Object>Loop_Col_DCT_Loop_proc</Object>
<Type>return value</Type>
<Scope></Scope>
<IOProtocol>ap_ctrl_hs</IOProtocol>
<IOConfig></IOConfig>
<Dir>in</Dir>
<Bits>1</Bits>
<Attribute>control</Attribute>
</RtlPorts>
<RtlPorts>
<name>ap_done</name>
<Object>Loop_Col_DCT_Loop_proc</Object>
<Type>return value</Type>
<Scope></Scope>
<IOProtocol>ap_ctrl_hs</IOProtocol>
<IOConfig></IOConfig>
<Dir>out</Dir>
<Bits>1</Bits>
<Attribute>control</Attribute>
</RtlPorts>
<RtlPorts>
<name>ap_continue</name>
<Object>Loop_Col_DCT_Loop_proc</Object>
<Type>return value</Type>
<Scope></Scope>
<IOProtocol>ap_ctrl_hs</IOProtocol>
<IOConfig></IOConfig>
<Dir>in</Dir>
<Bits>1</Bits>
<Attribute>control</Attribute>
</RtlPorts>
<RtlPorts>
<name>ap_idle</name>
<Object>Loop_Col_DCT_Loop_proc</Object>
<Type>return value</Type>
<Scope></Scope>
<IOProtocol>ap_ctrl_hs</IOProtocol>
<IOConfig></IOConfig>
<Dir>out</Dir>
<Bits>1</Bits>
<Attribute>control</Attribute>
</RtlPorts>
<RtlPorts>
<name>ap_ready</name>
<Object>Loop_Col_DCT_Loop_proc</Object>
<Type>return value</Type>
<Scope></Scope>
<IOProtocol>ap_ctrl_hs</IOProtocol>
<IOConfig></IOConfig>
<Dir>out</Dir>
<Bits>1</Bits>
<Attribute>control</Attribute>
</RtlPorts>
<RtlPorts>
<name>col_inbuf_i_0_address0</name>
<Object>col_inbuf_i_0</Object>
<Type>array</Type>
<Scope></Scope>
<IOProtocol>ap_memory</IOProtocol>
<IOConfig></IOConfig>
<Dir>out</Dir>
<Bits>3</Bits>
<Attribute>address</Attribute>
</RtlPorts>
<RtlPorts>
<name>col_inbuf_i_0_ce0</name>
<Object>col_inbuf_i_0</Object>
<Type>array</Type>
<Scope></Scope>
<IOProtocol>ap_memory</IOProtocol>
<IOConfig></IOConfig>
<Dir>out</Dir>
<Bits>1</Bits>
<Attribute>control</Attribute>
</RtlPorts>
<RtlPorts>
<name>col_inbuf_i_0_q0</name>
<Object>col_inbuf_i_0</Object>
<Type>array</Type>
<Scope></Scope>
<IOProtocol>ap_memory</IOProtocol>
<IOConfig></IOConfig>
<Dir>in</Dir>
<Bits>16</Bits>
<Attribute>data</Attribute>
</RtlPorts>
<RtlPorts>
<name>col_inbuf_i_1_address0</name>
<Object>col_inbuf_i_1</Object>
<Type>array</Type>
<Scope></Scope>
<IOProtocol>ap_memory</IOProtocol>
<IOConfig></IOConfig>
<Dir>out</Dir>
<Bits>3</Bits>
<Attribute>address</Attribute>
</RtlPorts>
<RtlPorts>
<name>col_inbuf_i_1_ce0</name>
<Object>col_inbuf_i_1</Object>
<Type>array</Type>
<Scope></Scope>
<IOProtocol>ap_memory</IOProtocol>
<IOConfig></IOConfig>
<Dir>out</Dir>
<Bits>1</Bits>
<Attribute>control</Attribute>
</RtlPorts>
<RtlPorts>
<name>col_inbuf_i_1_q0</name>
<Object>col_inbuf_i_1</Object>
<Type>array</Type>
<Scope></Scope>
<IOProtocol>ap_memory</IOProtocol>
<IOConfig></IOConfig>
<Dir>in</Dir>
<Bits>16</Bits>
<Attribute>data</Attribute>
</RtlPorts>
<RtlPorts>
<name>col_inbuf_i_2_address0</name>
<Object>col_inbuf_i_2</Object>
<Type>array</Type>
<Scope></Scope>
<IOProtocol>ap_memory</IOProtocol>
<IOConfig></IOConfig>
<Dir>out</Dir>
<Bits>3</Bits>
<Attribute>address</Attribute>
</RtlPorts>
<RtlPorts>
<name>col_inbuf_i_2_ce0</name>
<Object>col_inbuf_i_2</Object>
<Type>array</Type>
<Scope></Scope>
<IOProtocol>ap_memory</IOProtocol>
<IOConfig></IOConfig>
<Dir>out</Dir>
<Bits>1</Bits>
<Attribute>control</Attribute>
</RtlPorts>
<RtlPorts>
<name>col_inbuf_i_2_q0</name>
<Object>col_inbuf_i_2</Object>
<Type>array</Type>
<Scope></Scope>
<IOProtocol>ap_memory</IOProtocol>
<IOConfig></IOConfig>
<Dir>in</Dir>
<Bits>16</Bits>
<Attribute>data</Attribute>
</RtlPorts>
<RtlPorts>
<name>col_inbuf_i_3_address0</name>
<Object>col_inbuf_i_3</Object>
<Type>array</Type>
<Scope></Scope>
<IOProtocol>ap_memory</IOProtocol>
<IOConfig></IOConfig>
<Dir>out</Dir>
<Bits>3</Bits>
<Attribute>address</Attribute>
</RtlPorts>
<RtlPorts>
<name>col_inbuf_i_3_ce0</name>
<Object>col_inbuf_i_3</Object>
<Type>array</Type>
<Scope></Scope>
<IOProtocol>ap_memory</IOProtocol>
<IOConfig></IOConfig>
<Dir>out</Dir>
<Bits>1</Bits>
<Attribute>control</Attribute>
</RtlPorts>
<RtlPorts>
<name>col_inbuf_i_3_q0</name>
<Object>col_inbuf_i_3</Object>
<Type>array</Type>
<Scope></Scope>
<IOProtocol>ap_memory</IOProtocol>
<IOConfig></IOConfig>
<Dir>in</Dir>
<Bits>16</Bits>
<Attribute>data</Attribute>
</RtlPorts>
<RtlPorts>
<name>col_inbuf_i_4_address0</name>
<Object>col_inbuf_i_4</Object>
<Type>array</Type>
<Scope></Scope>
<IOProtocol>ap_memory</IOProtocol>
<IOConfig></IOConfig>
<Dir>out</Dir>
<Bits>3</Bits>
<Attribute>address</Attribute>
</RtlPorts>
<RtlPorts>
<name>col_inbuf_i_4_ce0</name>
<Object>col_inbuf_i_4</Object>
<Type>array</Type>
<Scope></Scope>
<IOProtocol>ap_memory</IOProtocol>
<IOConfig></IOConfig>
<Dir>out</Dir>
<Bits>1</Bits>
<Attribute>control</Attribute>
</RtlPorts>
<RtlPorts>
<name>col_inbuf_i_4_q0</name>
<Object>col_inbuf_i_4</Object>
<Type>array</Type>
<Scope></Scope>
<IOProtocol>ap_memory</IOProtocol>
<IOConfig></IOConfig>
<Dir>in</Dir>
<Bits>16</Bits>
<Attribute>data</Attribute>
</RtlPorts>
<RtlPorts>
<name>col_inbuf_i_5_address0</name>
<Object>col_inbuf_i_5</Object>
<Type>array</Type>
<Scope></Scope>
<IOProtocol>ap_memory</IOProtocol>
<IOConfig></IOConfig>
<Dir>out</Dir>
<Bits>3</Bits>
<Attribute>address</Attribute>
</RtlPorts>
<RtlPorts>
<name>col_inbuf_i_5_ce0</name>
<Object>col_inbuf_i_5</Object>
<Type>array</Type>
<Scope></Scope>
<IOProtocol>ap_memory</IOProtocol>
<IOConfig></IOConfig>
<Dir>out</Dir>
<Bits>1</Bits>
<Attribute>control</Attribute>
</RtlPorts>
<RtlPorts>
<name>col_inbuf_i_5_q0</name>
<Object>col_inbuf_i_5</Object>
<Type>array</Type>
<Scope></Scope>
<IOProtocol>ap_memory</IOProtocol>
<IOConfig></IOConfig>
<Dir>in</Dir>
<Bits>16</Bits>
<Attribute>data</Attribute>
</RtlPorts>
<RtlPorts>
<name>col_inbuf_i_6_address0</name>
<Object>col_inbuf_i_6</Object>
<Type>array</Type>
<Scope></Scope>
<IOProtocol>ap_memory</IOProtocol>
<IOConfig></IOConfig>
<Dir>out</Dir>
<Bits>3</Bits>
<Attribute>address</Attribute>
</RtlPorts>
<RtlPorts>
<name>col_inbuf_i_6_ce0</name>
<Object>col_inbuf_i_6</Object>
<Type>array</Type>
<Scope></Scope>
<IOProtocol>ap_memory</IOProtocol>
<IOConfig></IOConfig>
<Dir>out</Dir>
<Bits>1</Bits>
<Attribute>control</Attribute>
</RtlPorts>
<RtlPorts>
<name>col_inbuf_i_6_q0</name>
<Object>col_inbuf_i_6</Object>
<Type>array</Type>
<Scope></Scope>
<IOProtocol>ap_memory</IOProtocol>
<IOConfig></IOConfig>
<Dir>in</Dir>
<Bits>16</Bits>
<Attribute>data</Attribute>
</RtlPorts>
<RtlPorts>
<name>col_inbuf_i_7_address0</name>
<Object>col_inbuf_i_7</Object>
<Type>array</Type>
<Scope></Scope>
<IOProtocol>ap_memory</IOProtocol>
<IOConfig></IOConfig>
<Dir>out</Dir>
<Bits>3</Bits>
<Attribute>address</Attribute>
</RtlPorts>
<RtlPorts>
<name>col_inbuf_i_7_ce0</name>
<Object>col_inbuf_i_7</Object>
<Type>array</Type>
<Scope></Scope>
<IOProtocol>ap_memory</IOProtocol>
<IOConfig></IOConfig>
<Dir>out</Dir>
<Bits>1</Bits>
<Attribute>control</Attribute>
</RtlPorts>
<RtlPorts>
<name>col_inbuf_i_7_q0</name>
<Object>col_inbuf_i_7</Object>
<Type>array</Type>
<Scope></Scope>
<IOProtocol>ap_memory</IOProtocol>
<IOConfig></IOConfig>
<Dir>in</Dir>
<Bits>16</Bits>
<Attribute>data</Attribute>
</RtlPorts>
<RtlPorts>
<name>col_outbuf_i_address0</name>
<Object>col_outbuf_i</Object>
<Type>array</Type>
<Scope></Scope>
<IOProtocol>ap_memory</IOProtocol>
<IOConfig></IOConfig>
<Dir>out</Dir>
<Bits>6</Bits>
<Attribute>address</Attribute>
</RtlPorts>
<RtlPorts>
<name>col_outbuf_i_ce0</name>
<Object>col_outbuf_i</Object>
<Type>array</Type>
<Scope></Scope>
<IOProtocol>ap_memory</IOProtocol>
<IOConfig></IOConfig>
<Dir>out</Dir>
<Bits>1</Bits>
<Attribute>control</Attribute>
</RtlPorts>
<RtlPorts>
<name>col_outbuf_i_we0</name>
<Object>col_outbuf_i</Object>
<Type>array</Type>
<Scope></Scope>
<IOProtocol>ap_memory</IOProtocol>
<IOConfig></IOConfig>
<Dir>out</Dir>
<Bits>1</Bits>
<Attribute>control</Attribute>
</RtlPorts>
<RtlPorts>
<name>col_outbuf_i_d0</name>
<Object>col_outbuf_i</Object>
<Type>array</Type>
<Scope></Scope>
<IOProtocol>ap_memory</IOProtocol>
<IOConfig></IOConfig>
<Dir>out</Dir>
<Bits>16</Bits>
<Attribute>data</Attribute>
</RtlPorts>
</InterfaceSummary>
</Module>
<Module>
<Name>Loop_Xpose_Col_Outer_Loop_proc</Name>
<Loops>
<Xpose_Col_Outer_Loop_Xpose_Col_Inner_Loop></Xpose_Col_Outer_Loop_Xpose_Col_Inner_Loop>
</Loops>
<PerformanceEstimates>
<SummaryOfTimingAnalysis>
<TargetClockPeriod>10.00</TargetClockPeriod>
<ClockUncertainty>2.70</ClockUncertainty>
<EstimatedClockPeriod>6.508</EstimatedClockPeriod>
</SummaryOfTimingAnalysis>
<SummaryOfOverallLatency>
<Best-caseLatency>67</Best-caseLatency>
<Average-caseLatency>67</Average-caseLatency>
<Worst-caseLatency>67</Worst-caseLatency>
<Best-caseRealTimeLatency>0.670 us</Best-caseRealTimeLatency>
<Average-caseRealTimeLatency>0.670 us</Average-caseRealTimeLatency>
<Worst-caseRealTimeLatency>0.670 us</Worst-caseRealTimeLatency>
<PipelineInitiationInterval>65</PipelineInitiationInterval>
<PipelineType>loop auto-rewind stp (delay=1 clock cycles(s))</PipelineType>
</SummaryOfOverallLatency>
<SummaryOfLoopLatency>
<Xpose_Col_Outer_Loop_Xpose_Col_Inner_Loop>
<Name>Xpose_Col_Outer_Loop_Xpose_Col_Inner_Loop</Name>
<Slack>7.30</Slack>
<TripCount>64</TripCount>
<Latency>65</Latency>
<AbsoluteTimeLatency>0.650 us</AbsoluteTimeLatency>
<PipelineII>1</PipelineII>
<PipelineDepth>3</PipelineDepth>
<PipelineType>yes</PipelineType>
<InstanceList>
</InstanceList>
</Xpose_Col_Outer_Loop_Xpose_Col_Inner_Loop>
</SummaryOfLoopLatency>
<SummaryOfViolations>
<IssueType>-</IssueType>
<ViolationType>-</ViolationType>
<SourceLocation>E:/robot/project/xilinx_fpga_class/hls/lab3/dct.c:83</SourceLocation>
<SummaryOfLoopViolations>
<Xpose_Col_Outer_Loop_Xpose_Col_Inner_Loop>
<Name>Xpose_Col_Outer_Loop_Xpose_Col_Inner_Loop</Name>
<IssueType>-</IssueType>
<ViolationType>-</ViolationType>
<SourceLocation>E:/robot/project/xilinx_fpga_class/hls/lab3/dct.c:83</SourceLocation>
</Xpose_Col_Outer_Loop_Xpose_Col_Inner_Loop>
</SummaryOfLoopViolations>
</SummaryOfViolations>
</PerformanceEstimates>
<AreaEstimates>
<Resources>
<FF>43</FF>
<AVAIL_FF>106400</AVAIL_FF>
<UTIL_FF>~0</UTIL_FF>
<LUT>192</LUT>
<AVAIL_LUT>53200</AVAIL_LUT>
<UTIL_LUT>~0</UTIL_LUT>
<BRAM_18K>0</BRAM_18K>
<AVAIL_BRAM>280</AVAIL_BRAM>
<UTIL_BRAM>0</UTIL_BRAM>
<DSP>0</DSP>
<AVAIL_DSP>220</AVAIL_DSP>
<UTIL_DSP>0</UTIL_DSP>
<URAM>0</URAM>
<AVAIL_URAM>0</AVAIL_URAM>
<UTIL_URAM>0</UTIL_URAM>
</Resources>
</AreaEstimates>
<InterfaceSummary>
<RtlPorts>
<name>ap_clk</name>
<Object>Loop_Xpose_Col_Outer_Loop_proc</Object>
<Type>return value</Type>
<Scope></Scope>
<IOProtocol>ap_ctrl_hs</IOProtocol>
<IOConfig></IOConfig>
<Dir>in</Dir>
<Bits>1</Bits>
<Attribute>control</Attribute>
</RtlPorts>
<RtlPorts>
<name>ap_rst</name>
<Object>Loop_Xpose_Col_Outer_Loop_proc</Object>
<Type>return value</Type>
<Scope></Scope>
<IOProtocol>ap_ctrl_hs</IOProtocol>
<IOConfig></IOConfig>
<Dir>in</Dir>
<Bits>1</Bits>
<Attribute>control</Attribute>
</RtlPorts>
<RtlPorts>
<name>ap_start</name>
<Object>Loop_Xpose_Col_Outer_Loop_proc</Object>
<Type>return value</Type>
<Scope></Scope>
<IOProtocol>ap_ctrl_hs</IOProtocol>
<IOConfig></IOConfig>
<Dir>in</Dir>
<Bits>1</Bits>
<Attribute>control</Attribute>
</RtlPorts>
<RtlPorts>
<name>ap_done</name>
<Object>Loop_Xpose_Col_Outer_Loop_proc</Object>
<Type>return value</Type>
<Scope></Scope>
<IOProtocol>ap_ctrl_hs</IOProtocol>
<IOConfig></IOConfig>
<Dir>out</Dir>
<Bits>1</Bits>
<Attribute>control</Attribute>
</RtlPorts>
<RtlPorts>
<name>ap_continue</name>
<Object>Loop_Xpose_Col_Outer_Loop_proc</Object>
<Type>return value</Type>
<Scope></Scope>
<IOProtocol>ap_ctrl_hs</IOProtocol>
<IOConfig></IOConfig>
<Dir>in</Dir>
<Bits>1</Bits>
<Attribute>control</Attribute>
</RtlPorts>
<RtlPorts>
<name>ap_idle</name>
<Object>Loop_Xpose_Col_Outer_Loop_proc</Object>
<Type>return value</Type>
<Scope></Scope>
<IOProtocol>ap_ctrl_hs</IOProtocol>
<IOConfig></IOConfig>
<Dir>out</Dir>
<Bits>1</Bits>
<Attribute>control</Attribute>
</RtlPorts>
<RtlPorts>
<name>ap_ready</name>
<Object>Loop_Xpose_Col_Outer_Loop_proc</Object>
<Type>return value</Type>
<Scope></Scope>
<IOProtocol>ap_ctrl_hs</IOProtocol>
<IOConfig></IOConfig>
<Dir>out</Dir>
<Bits>1</Bits>
<Attribute>control</Attribute>
</RtlPorts>
<RtlPorts>
<name>col_outbuf_i_address0</name>
<Object>col_outbuf_i</Object>
<Type>array</Type>
<Scope></Scope>
<IOProtocol>ap_memory</IOProtocol>
<IOConfig></IOConfig>
<Dir>out</Dir>
<Bits>6</Bits>
<Attribute>address</Attribute>
</RtlPorts>
<RtlPorts>
<name>col_outbuf_i_ce0</name>
<Object>col_outbuf_i</Object>
<Type>array</Type>
<Scope></Scope>
<IOProtocol>ap_memory</IOProtocol>
<IOConfig></IOConfig>
<Dir>out</Dir>
<Bits>1</Bits>
<Attribute>control</Attribute>
</RtlPorts>
<RtlPorts>
<name>col_outbuf_i_q0</name>
<Object>col_outbuf_i</Object>
<Type>array</Type>
<Scope></Scope>
<IOProtocol>ap_memory</IOProtocol>
<IOConfig></IOConfig>
<Dir>in</Dir>
<Bits>16</Bits>
<Attribute>data</Attribute>
</RtlPorts>
<RtlPorts>
<name>buf_2d_out_address0</name>
<Object>buf_2d_out</Object>
<Type>array</Type>
<Scope></Scope>
<IOProtocol>ap_memory</IOProtocol>
<IOConfig></IOConfig>
<Dir>out</Dir>
<Bits>6</Bits>
<Attribute>address</Attribute>
</RtlPorts>
<RtlPorts>
<name>buf_2d_out_ce0</name>
<Object>buf_2d_out</Object>
<Type>array</Type>
<Scope></Scope>
<IOProtocol>ap_memory</IOProtocol>
<IOConfig></IOConfig>
<Dir>out</Dir>
<Bits>1</Bits>
<Attribute>control</Attribute>
</RtlPorts>
<RtlPorts>
<name>buf_2d_out_we0</name>
<Object>buf_2d_out</Object>
<Type>array</Type>
<Scope></Scope>
<IOProtocol>ap_memory</IOProtocol>
<IOConfig></IOConfig>
<Dir>out</Dir>
<Bits>1</Bits>
<Attribute>control</Attribute>
</RtlPorts>
<RtlPorts>
<name>buf_2d_out_d0</name>
<Object>buf_2d_out</Object>
<Type>array</Type>
<Scope></Scope>
<IOProtocol>ap_memory</IOProtocol>
<IOConfig></IOConfig>
<Dir>out</Dir>
<Bits>16</Bits>
<Attribute>data</Attribute>
</RtlPorts>
</InterfaceSummary>
</Module>
<Module>
<Name>write_data</Name>
<Loops>
<WR_Loop_Row_WR_Loop_Col></WR_Loop_Row_WR_Loop_Col>
</Loops>
<PerformanceEstimates>
<SummaryOfTimingAnalysis>
<TargetClockPeriod>10.00</TargetClockPeriod>
<ClockUncertainty>2.70</ClockUncertainty>
<EstimatedClockPeriod>6.508</EstimatedClockPeriod>
</SummaryOfTimingAnalysis>
<SummaryOfOverallLatency>
<Best-caseLatency>67</Best-caseLatency>
<Average-caseLatency>67</Average-caseLatency>
<Worst-caseLatency>67</Worst-caseLatency>
<Best-caseRealTimeLatency>0.670 us</Best-caseRealTimeLatency>
<Average-caseRealTimeLatency>0.670 us</Average-caseRealTimeLatency>
<Worst-caseRealTimeLatency>0.670 us</Worst-caseRealTimeLatency>
<PipelineInitiationInterval>65</PipelineInitiationInterval>
<PipelineType>loop auto-rewind stp (delay=1 clock cycles(s))</PipelineType>
</SummaryOfOverallLatency>
<SummaryOfLoopLatency>
<WR_Loop_Row_WR_Loop_Col>
<Name>WR_Loop_Row_WR_Loop_Col</Name>
<Slack>7.30</Slack>
<TripCount>64</TripCount>
<Latency>65</Latency>
<AbsoluteTimeLatency>0.650 us</AbsoluteTimeLatency>
<PipelineII>1</PipelineII>
<PipelineDepth>3</PipelineDepth>
<PipelineType>yes</PipelineType>
<InstanceList>
</InstanceList>
</WR_Loop_Row_WR_Loop_Col>
</SummaryOfLoopLatency>
<SummaryOfViolations>
<IssueType>-</IssueType>
<ViolationType>-</ViolationType>
<SourceLocation>E:/robot/project/xilinx_fpga_class/hls/lab3/dct.c:110</SourceLocation>
<SummaryOfLoopViolations>
<WR_Loop_Row_WR_Loop_Col>
<Name>WR_Loop_Row_WR_Loop_Col</Name>
<IssueType>-</IssueType>
<ViolationType>-</ViolationType>
<SourceLocation>E:/robot/project/xilinx_fpga_class/hls/lab3/dct.c:110</SourceLocation>
</WR_Loop_Row_WR_Loop_Col>
</SummaryOfLoopViolations>
</SummaryOfViolations>
</PerformanceEstimates>
<AreaEstimates>
<Resources>
<FF>36</FF>
<AVAIL_FF>106400</AVAIL_FF>
<UTIL_FF>~0</UTIL_FF>
<LUT>178</LUT>
<AVAIL_LUT>53200</AVAIL_LUT>
<UTIL_LUT>~0</UTIL_LUT>
<BRAM_18K>0</BRAM_18K>
<AVAIL_BRAM>280</AVAIL_BRAM>
<UTIL_BRAM>0</UTIL_BRAM>
<DSP>0</DSP>
<AVAIL_DSP>220</AVAIL_DSP>
<UTIL_DSP>0</UTIL_DSP>
<URAM>0</URAM>
<AVAIL_URAM>0</AVAIL_URAM>
<UTIL_URAM>0</UTIL_URAM>
</Resources>
</AreaEstimates>
<InterfaceSummary>
<RtlPorts>
<name>ap_clk</name>
<Object>write_data</Object>
<Type>return value</Type>
<Scope></Scope>
<IOProtocol>ap_ctrl_hs</IOProtocol>
<IOConfig></IOConfig>
<Dir>in</Dir>
<Bits>1</Bits>
<Attribute>control</Attribute>
</RtlPorts>
<RtlPorts>
<name>ap_rst</name>
<Object>write_data</Object>
<Type>return value</Type>
<Scope></Scope>
<IOProtocol>ap_ctrl_hs</IOProtocol>
<IOConfig></IOConfig>
<Dir>in</Dir>
<Bits>1</Bits>
<Attribute>control</Attribute>
</RtlPorts>
<RtlPorts>
<name>ap_start</name>
<Object>write_data</Object>
<Type>return value</Type>
<Scope></Scope>
<IOProtocol>ap_ctrl_hs</IOProtocol>
<IOConfig></IOConfig>
<Dir>in</Dir>
<Bits>1</Bits>
<Attribute>control</Attribute>
</RtlPorts>
<RtlPorts>
<name>ap_done</name>
<Object>write_data</Object>
<Type>return value</Type>
<Scope></Scope>
<IOProtocol>ap_ctrl_hs</IOProtocol>
<IOConfig></IOConfig>
<Dir>out</Dir>
<Bits>1</Bits>
<Attribute>control</Attribute>
</RtlPorts>
<RtlPorts>
<name>ap_continue</name>
<Object>write_data</Object>
<Type>return value</Type>
<Scope></Scope>
<IOProtocol>ap_ctrl_hs</IOProtocol>
<IOConfig></IOConfig>
<Dir>in</Dir>
<Bits>1</Bits>
<Attribute>control</Attribute>
</RtlPorts>
<RtlPorts>
<name>ap_idle</name>
<Object>write_data</Object>
<Type>return value</Type>
<Scope></Scope>
<IOProtocol>ap_ctrl_hs</IOProtocol>
<IOConfig></IOConfig>
<Dir>out</Dir>
<Bits>1</Bits>
<Attribute>control</Attribute>
</RtlPorts>
<RtlPorts>
<name>ap_ready</name>
<Object>write_data</Object>
<Type>return value</Type>
<Scope></Scope>
<IOProtocol>ap_ctrl_hs</IOProtocol>
<IOConfig></IOConfig>
<Dir>out</Dir>
<Bits>1</Bits>
<Attribute>control</Attribute>
</RtlPorts>
<RtlPorts>
<name>buf_r_address0</name>
<Object>buf_r</Object>
<Type>array</Type>
<Scope></Scope>
<IOProtocol>ap_memory</IOProtocol>
<IOConfig></IOConfig>
<Dir>out</Dir>
<Bits>6</Bits>
<Attribute>address</Attribute>
</RtlPorts>
<RtlPorts>
<name>buf_r_ce0</name>
<Object>buf_r</Object>
<Type>array</Type>
<Scope></Scope>
<IOProtocol>ap_memory</IOProtocol>
<IOConfig></IOConfig>
<Dir>out</Dir>
<Bits>1</Bits>
<Attribute>control</Attribute>
</RtlPorts>
<RtlPorts>
<name>buf_r_q0</name>
<Object>buf_r</Object>
<Type>array</Type>
<Scope></Scope>
<IOProtocol>ap_memory</IOProtocol>
<IOConfig></IOConfig>
<Dir>in</Dir>
<Bits>16</Bits>
<Attribute>data</Attribute>
</RtlPorts>
<RtlPorts>
<name>output_r_address0</name>
<Object>output_r</Object>
<Type>array</Type>
<Scope></Scope>
<IOProtocol>ap_memory</IOProtocol>
<IOConfig></IOConfig>
<Dir>out</Dir>
<Bits>6</Bits>
<Attribute>address</Attribute>
</RtlPorts>
<RtlPorts>
<name>output_r_ce0</name>
<Object>output_r</Object>
<Type>array</Type>
<Scope></Scope>
<IOProtocol>ap_memory</IOProtocol>
<IOConfig></IOConfig>
<Dir>out</Dir>
<Bits>1</Bits>
<Attribute>control</Attribute>
</RtlPorts>
<RtlPorts>
<name>output_r_we0</name>
<Object>output_r</Object>
<Type>array</Type>
<Scope></Scope>
<IOProtocol>ap_memory</IOProtocol>
<IOConfig></IOConfig>
<Dir>out</Dir>
<Bits>1</Bits>
<Attribute>control</Attribute>
</RtlPorts>
<RtlPorts>
<name>output_r_d0</name>
<Object>output_r</Object>
<Type>array</Type>
<Scope></Scope>
<IOProtocol>ap_memory</IOProtocol>
<IOConfig></IOConfig>
<Dir>out</Dir>
<Bits>16</Bits>
<Attribute>data</Attribute>
</RtlPorts>
</InterfaceSummary>
</Module>
<Module>
<Name>dct</Name>
<PerformanceEstimates>
<SummaryOfTimingAnalysis>
<TargetClockPeriod>10.00</TargetClockPeriod>
<ClockUncertainty>2.70</ClockUncertainty>
<EstimatedClockPeriod>6.669</EstimatedClockPeriod>
</SummaryOfTimingAnalysis>
<SummaryOfOverallLatency>
<Best-caseLatency>417</Best-caseLatency>
<Average-caseLatency>417</Average-caseLatency>
<Worst-caseLatency>417</Worst-caseLatency>
<Best-caseRealTimeLatency>4.170 us</Best-caseRealTimeLatency>
<Average-caseRealTimeLatency>4.170 us</Average-caseRealTimeLatency>
<Worst-caseRealTimeLatency>4.170 us</Worst-caseRealTimeLatency>
<DataflowPipelineThroughput>64</DataflowPipelineThroughput>
<PipelineInitiationInterval>64</PipelineInitiationInterval>
<PipelineType>dataflow</PipelineType>
</SummaryOfOverallLatency>
<SummaryOfViolations>
<IssueType>-</IssueType>
<ViolationType>-</ViolationType>
<SourceLocation>E:/robot/project/xilinx_fpga_class/hls/lab3/dct.c:119</SourceLocation>
</SummaryOfViolations>
</PerformanceEstimates>
<AreaEstimates>
<Resources>
<BRAM_18K>3</BRAM_18K>
<AVAIL_BRAM>280</AVAIL_BRAM>
<UTIL_BRAM>1</UTIL_BRAM>
<DSP>16</DSP>
<AVAIL_DSP>220</AVAIL_DSP>
<UTIL_DSP>7</UTIL_DSP>
<FF>1790</FF>
<AVAIL_FF>106400</AVAIL_FF>
<UTIL_FF>1</UTIL_FF>
<LUT>1558</LUT>
<AVAIL_LUT>53200</AVAIL_LUT>
<UTIL_LUT>2</UTIL_LUT>
<URAM>0</URAM>
<AVAIL_URAM>0</AVAIL_URAM>
<UTIL_URAM>0</UTIL_URAM>
</Resources>
</AreaEstimates>
<InterfaceSummary>
<RtlPorts>
<name>ap_clk</name>
<Object>dct</Object>
<Type>return value</Type>
<Scope></Scope>
<IOProtocol>ap_ctrl_hs</IOProtocol>
<IOConfig></IOConfig>
<Dir>in</Dir>
<Bits>1</Bits>
<Attribute>control</Attribute>
</RtlPorts>
<RtlPorts>
<name>ap_rst</name>
<Object>dct</Object>
<Type>return value</Type>
<Scope></Scope>
<IOProtocol>ap_ctrl_hs</IOProtocol>
<IOConfig></IOConfig>
<Dir>in</Dir>
<Bits>1</Bits>
<Attribute>control</Attribute>
</RtlPorts>
<RtlPorts>
<name>ap_start</name>
<Object>dct</Object>
<Type>return value</Type>
<Scope></Scope>
<IOProtocol>ap_ctrl_hs</IOProtocol>
<IOConfig></IOConfig>
<Dir>in</Dir>
<Bits>1</Bits>
<Attribute>control</Attribute>
</RtlPorts>
<RtlPorts>
<name>ap_done</name>
<Object>dct</Object>
<Type>return value</Type>
<Scope></Scope>
<IOProtocol>ap_ctrl_hs</IOProtocol>
<IOConfig></IOConfig>
<Dir>out</Dir>
<Bits>1</Bits>
<Attribute>control</Attribute>
</RtlPorts>
<RtlPorts>
<name>ap_ready</name>
<Object>dct</Object>
<Type>return value</Type>
<Scope></Scope>
<IOProtocol>ap_ctrl_hs</IOProtocol>
<IOConfig></IOConfig>
<Dir>out</Dir>
<Bits>1</Bits>
<Attribute>control</Attribute>
</RtlPorts>
<RtlPorts>
<name>ap_idle</name>
<Object>dct</Object>
<Type>return value</Type>
<Scope></Scope>
<IOProtocol>ap_ctrl_hs</IOProtocol>
<IOConfig></IOConfig>
<Dir>out</Dir>
<Bits>1</Bits>
<Attribute>control</Attribute>
</RtlPorts>
<RtlPorts>
<name>input_r_address0</name>
<Object>input_r</Object>
<Type>array</Type>
<Scope></Scope>
<IOProtocol>ap_memory</IOProtocol>
<IOConfig></IOConfig>
<Dir>out</Dir>
<Bits>6</Bits>
<Attribute>address</Attribute>
<CType>int</CType>
</RtlPorts>
<RtlPorts>
<name>input_r_ce0</name>
<Object>input_r</Object>
<Type>array</Type>
<Scope></Scope>
<IOProtocol>ap_memory</IOProtocol>
<IOConfig></IOConfig>
<Dir>out</Dir>
<Bits>1</Bits>
<Attribute>control</Attribute>
<CType>int</CType>
</RtlPorts>
<RtlPorts>
<name>input_r_d0</name>
<Object>input_r</Object>
<Type>array</Type>
<Scope></Scope>
<IOProtocol>ap_memory</IOProtocol>
<IOConfig></IOConfig>
<Dir>out</Dir>
<Bits>16</Bits>
<Attribute>data</Attribute>
<CType>int</CType>
</RtlPorts>
<RtlPorts>
<name>input_r_q0</name>
<Object>input_r</Object>
<Type>array</Type>
<Scope></Scope>
<IOProtocol>ap_memory</IOProtocol>
<IOConfig></IOConfig>
<Dir>in</Dir>
<Bits>16</Bits>
<Attribute>data</Attribute>
<CType>int</CType>
</RtlPorts>
<RtlPorts>
<name>input_r_we0</name>
<Object>input_r</Object>
<Type>array</Type>
<Scope></Scope>
<IOProtocol>ap_memory</IOProtocol>
<IOConfig></IOConfig>
<Dir>out</Dir>
<Bits>1</Bits>
<Attribute>control</Attribute>
<CType>int</CType>
</RtlPorts>
<RtlPorts>
<name>input_r_address1</name>
<Object>input_r</Object>
<Type>array</Type>
<Scope></Scope>
<IOProtocol>ap_memory</IOProtocol>
<IOConfig></IOConfig>
<Dir>out</Dir>
<Bits>6</Bits>
<Attribute>address</Attribute>
<CType>int</CType>
</RtlPorts>
<RtlPorts>
<name>input_r_ce1</name>
<Object>input_r</Object>
<Type>array</Type>
<Scope></Scope>
<IOProtocol>ap_memory</IOProtocol>
<IOConfig></IOConfig>
<Dir>out</Dir>
<Bits>1</Bits>
<Attribute>control</Attribute>
<CType>int</CType>
</RtlPorts>
<RtlPorts>
<name>input_r_d1</name>
<Object>input_r</Object>
<Type>array</Type>
<Scope></Scope>
<IOProtocol>ap_memory</IOProtocol>
<IOConfig></IOConfig>
<Dir>out</Dir>
<Bits>16</Bits>
<Attribute>data</Attribute>
<CType>int</CType>
</RtlPorts>
<RtlPorts>
<name>input_r_q1</name>
<Object>input_r</Object>
<Type>array</Type>
<Scope></Scope>
<IOProtocol>ap_memory</IOProtocol>
<IOConfig></IOConfig>
<Dir>in</Dir>
<Bits>16</Bits>
<Attribute>data</Attribute>
<CType>int</CType>
</RtlPorts>
<RtlPorts>
<name>input_r_we1</name>
<Object>input_r</Object>
<Type>array</Type>
<Scope></Scope>
<IOProtocol>ap_memory</IOProtocol>
<IOConfig></IOConfig>
<Dir>out</Dir>
<Bits>1</Bits>
<Attribute>control</Attribute>
<CType>int</CType>
</RtlPorts>
<RtlPorts>
<name>output_r_address0</name>
<Object>output_r</Object>
<Type>array</Type>
<Scope></Scope>
<IOProtocol>ap_memory</IOProtocol>
<IOConfig></IOConfig>
<Dir>out</Dir>
<Bits>6</Bits>
<Attribute>address</Attribute>
<CType>int</CType>
</RtlPorts>
<RtlPorts>
<name>output_r_ce0</name>
<Object>output_r</Object>
<Type>array</Type>
<Scope></Scope>
<IOProtocol>ap_memory</IOProtocol>
<IOConfig></IOConfig>
<Dir>out</Dir>
<Bits>1</Bits>
<Attribute>control</Attribute>
<CType>int</CType>
</RtlPorts>
<RtlPorts>
<name>output_r_d0</name>
<Object>output_r</Object>
<Type>array</Type>
<Scope></Scope>
<IOProtocol>ap_memory</IOProtocol>
<IOConfig></IOConfig>
<Dir>out</Dir>
<Bits>16</Bits>
<Attribute>data</Attribute>
<CType>int</CType>
</RtlPorts>
<RtlPorts>
<name>output_r_q0</name>
<Object>output_r</Object>
<Type>array</Type>
<Scope></Scope>
<IOProtocol>ap_memory</IOProtocol>
<IOConfig></IOConfig>
<Dir>in</Dir>
<Bits>16</Bits>
<Attribute>data</Attribute>
<CType>int</CType>
</RtlPorts>
<RtlPorts>
<name>output_r_we0</name>
<Object>output_r</Object>
<Type>array</Type>
<Scope></Scope>
<IOProtocol>ap_memory</IOProtocol>
<IOConfig></IOConfig>
<Dir>out</Dir>
<Bits>1</Bits>
<Attribute>control</Attribute>
<CType>int</CType>
</RtlPorts>
<RtlPorts>
<name>output_r_address1</name>
<Object>output_r</Object>
<Type>array</Type>
<Scope></Scope>
<IOProtocol>ap_memory</IOProtocol>
<IOConfig></IOConfig>
<Dir>out</Dir>
<Bits>6</Bits>
<Attribute>address</Attribute>
<CType>int</CType>
</RtlPorts>
<RtlPorts>
<name>output_r_ce1</name>
<Object>output_r</Object>
<Type>array</Type>
<Scope></Scope>
<IOProtocol>ap_memory</IOProtocol>
<IOConfig></IOConfig>
<Dir>out</Dir>
<Bits>1</Bits>
<Attribute>control</Attribute>
<CType>int</CType>
</RtlPorts>
<RtlPorts>
<name>output_r_d1</name>
<Object>output_r</Object>
<Type>array</Type>
<Scope></Scope>
<IOProtocol>ap_memory</IOProtocol>
<IOConfig></IOConfig>
<Dir>out</Dir>
<Bits>16</Bits>
<Attribute>data</Attribute>
<CType>int</CType>
</RtlPorts>
<RtlPorts>
<name>output_r_q1</name>
<Object>output_r</Object>
<Type>array</Type>
<Scope></Scope>
<IOProtocol>ap_memory</IOProtocol>
<IOConfig></IOConfig>
<Dir>in</Dir>
<Bits>16</Bits>
<Attribute>data</Attribute>
<CType>int</CType>
</RtlPorts>
<RtlPorts>
<name>output_r_we1</name>
<Object>output_r</Object>
<Type>array</Type>
<Scope></Scope>
<IOProtocol>ap_memory</IOProtocol>
<IOConfig></IOConfig>
<Dir>out</Dir>
<Bits>1</Bits>
<Attribute>control</Attribute>
<CType>int</CType>
</RtlPorts>
</InterfaceSummary>
</Module>
</ModuleInformation>

<FIFOInformation>
</FIFOInformation>

</profile>
